bluelight/__init__.py
bluelight/bluetooth_monitor.py
bluelight/company_identifiers.json
bluelight/config.py
bluelight/main.py
bluelight/utils.py
bluelight-0.1.0.dist-info/METADATA
bluelight-0.1.0.dist-info/WHEEL
bluelight-0.1.0.dist-info/entry_points.txt
bluelight-0.1.0.dist-info/RECORD
